drfsc/__init__.py
drfsc/drfsc.py
drfsc/rfsc.py
drfsc/utils.py
drfsc-0.0.7.dist-info/LICENSE
drfsc-0.0.7.dist-info/METADATA
drfsc-0.0.7.dist-info/WHEEL
drfsc-0.0.7.dist-info/top_level.txt
drfsc-0.0.7.dist-info/RECORD
