Metadata-Version: 2.1
Name: drfsc
Version: 0.0.7
Summary: A Python package implementing a distributed randomised feature selection algorithm.
Author-email: Mark Chiu Chong <mark.chiuchong@gmail.com>
Project-URL: Homepage, https://github.com/markcc309/drfsc
Project-URL: Documentation, https://markcc309.github.io/drfsc/
Classifier: Topic :: Scientific/Engineering
Classifier: Programming Language :: Python :: 3
Classifier: License :: OSI Approved :: MIT License
Classifier: Operating System :: OS Independent
Classifier: Intended Audience :: Science/Research
Requires-Python: >=3.9.12
License-File: LICENSE
Requires-Dist: numpy (==1.23.4)
Requires-Dist: pandas (==1.5.2)
Requires-Dist: pip (==22.3.1)
Requires-Dist: scikit-learn (==1.1.2)
Requires-Dist: setuptools (==65.5.0)
Requires-Dist: statsmodels (==0.13.2)
Requires-Dist: matplotlib (==3.6.2)
Requires-Dist: toml (==0.10.2)
Requires-Dist: wheel (==0.37.1)
Provides-Extra: tests
Requires-Dist: pytest (==7.1.2) ; extra == 'tests'
